{
	"id": "S2fqMCEdzqDoX02",
	"json": "{\"id\":\"S2fqMCEdzqDoX02\",\"url\":\"https://www.basketball-reference.com/search/search.fcgi?search=T.J.%20McConnell\",\"loadedUrl\":\"https://www.basketball-reference.com/search/search.fcgi?search=T.J.%20McConnell\",\"uniqueKey\":\"https://www.basketball-reference.com/search/search.fcgi?search=T.J.+McConnell\",\"method\":\"GET\",\"noRetry\":false,\"retryCount\":0,\"errorMessages\":[],\"headers\":{},\"userData\":{\"__crawlee\":{\"state\":4}},\"handledAt\":\"2026-04-23T13:43:24.588Z\"}",
	"method": "GET",
	"orderNo": null,
	"retryCount": 0,
	"uniqueKey": "https://www.basketball-reference.com/search/search.fcgi?search=T.J.+McConnell",
	"url": "https://www.basketball-reference.com/search/search.fcgi?search=T.J.%20McConnell"
}